pyllelic/__init__.py
pyllelic/__main__.py
pyllelic/__version__.py
pyllelic/config.py
pyllelic/process.py
pyllelic/pyllelic.py
pyllelic/quma.py
pyllelic/visualization.py
pyllelic-0.4.8.dist-info/LICENSE
pyllelic-0.4.8.dist-info/METADATA
pyllelic-0.4.8.dist-info/WHEEL
pyllelic-0.4.8.dist-info/top_level.txt
pyllelic-0.4.8.dist-info/RECORD
