Metadata-Version: 2.1
Name: pyllelic
Version: 0.4.8
Summary: Analysis of allele-specific methylation in bisulfite DNA sequencing.
Author-email: "Andrew J. Bonham" <bonham@gmail.com>
License: GNU GENERAL PUBLIC LICENSE
Project-URL: Homepage, https://github.com/Paradoxdruid/pyllelic
Keywords: genomics,methylation,DNA sequencing
Classifier: Programming Language :: Python :: 3
Classifier: Programming Language :: Python :: 3.8
Classifier: Programming Language :: Python :: 3.9
Classifier: Programming Language :: Python :: 3.10
Classifier: Programming Language :: Python :: 3 :: Only
Classifier: License :: OSI Approved :: GNU General Public License v3 (GPLv3)
Classifier: Operating System :: OS Independent
Requires-Python: >=3.8
License-File: LICENSE
Requires-Dist: pandas
Requires-Dist: numpy
Requires-Dist: scipy
Requires-Dist: plotly
Requires-Dist: matplotlib
Requires-Dist: xlsxwriter
Requires-Dist: xlrd
Requires-Dist: openpyxl
Requires-Dist: tqdm
Requires-Dist: pysam
Requires-Dist: biopython
Requires-Dist: seaborn
Requires-Dist: requests
Provides-Extra: dev
Requires-Dist: black ; extra == 'dev'
Requires-Dist: pytest ; extra == 'dev'
Requires-Dist: pytest-mock ; extra == 'dev'
Requires-Dist: mypy ; extra == 'dev'
Requires-Dist: types-requests ; extra == 'dev'
Requires-Dist: ruff ; extra == 'dev'
Requires-Dist: requests-mock ; extra == 'dev'
Requires-Dist: pre-commit ; extra == 'dev'
